<?xml version="1.0" encoding="UTF-8"?>
<list xmlns:ns0="http://www.w3.org/2001/XMLSchema-instance" ns0:noNamespaceSchemaLocation="multisell.xsd">
	<item id="1">
		<!-- Memento Mori -->
		<ingredient count="20" id="9814" />
		<!-- Earth Egg -->
		<ingredient count="22" id="9816" />
		<!-- Angelic Essence -->
		<ingredient count="4" id="9818" />
		<!-- Chain Hood -->
		<production count="1" id="2413" />
	</item>
	<item id="2">
		<!-- Memento Mori -->
		<ingredient count="26" id="9814" />
		<!-- Earth Egg -->
		<ingredient count="28" id="9816" />
		<!-- Angelic Essence -->
		<ingredient count="4" id="9818" />
		<!-- Great Helmet -->
		<production count="1" id="500" />
	</item>
	<item id="3">
		<!-- Memento Mori -->
		<ingredient count="42" id="9814" />
		<!-- Earth Egg -->
		<ingredient count="46" id="9816" />
		<!-- Angelic Essence -->
		<ingredient count="8" id="9818" />
		<!-- Composite Helmet -->
		<production count="1" id="517" />
	</item>
	<item id="4">
		<!-- Memento Mori -->
		<ingredient count="42" id="9814" />
		<!-- Earth Egg -->
		<ingredient count="46" id="9816" />
		<!-- Angelic Essence -->
		<ingredient count="8" id="9818" />
		<!-- Shining Circlet -->
		<production count="1" id="1149" />
	</item>
	<item id="5">
		<!-- Memento Mori -->
		<ingredient count="62" id="9814" />
		<!-- Earth Egg -->
		<ingredient count="66" id="9816" />
		<!-- Angelic Essence -->
		<ingredient count="12" id="9818" />
		<!-- Composite Armor -->
		<production count="1" id="60" />
	</item>
</list>
