<?xml version="1.0" encoding="UTF-8"?>
<list>
	<skill id="3700" levels="1" name="Doom Shield">
		<!-- Confirmed CT2.5 -->
		<set name="target" val="TARGET_SELF" />
		<set name="skillType" val="BUFF" />
		<set name="operateType" val="OP_PASSIVE" />
		<for>
			<mul order="0x30" stat="mDef" val="1.02" />
		</for>
	</skill>
	<skill id="3701" levels="1" name="Leather Armor of Doom">
		<!-- It has been changed so that a rare type upper armor is not manufactured during item creation. -->
		<set name="target" val="TARGET_NONE" />
		<set name="skillType" val="NOTDONE" />
		<set name="operateType" val="OP_PASSIVE" />
	</skill>
	<skill id="3702" levels="1" name="Doom Gloves">
		<!-- Confirmed CT2.5 -->
		<set name="target" val="TARGET_SELF" />
		<set name="skillType" val="BUFF" />
		<set name="operateType" val="OP_PASSIVE" />
		<for>
			<add order="0x40" stat="breath" val="33" />
			<mul order="0x30" stat="pAtk" val="1.0041" />
			<mul order="0x30" stat="regMp" val="1.0041" />
			<sub order="0x40" stat="poisonVuln" val="2" />
		</for>
	</skill>
	<skill id="3703" levels="1" name="Doom Boots">
		<!-- Confirmed CT2.5 -->
		<set name="target" val="TARGET_SELF" />
		<set name="skillType" val="BUFF" />
		<set name="operateType" val="OP_PASSIVE" />
		<for>
			<add order="0x40" stat="breath" val="33" />
			<mul order="0x30" stat="pAtk" val="1.0041" />
			<mul order="0x30" stat="regMp" val="1.0041" />
			<sub order="0x40" stat="poisonVuln" val="3" />
		</for>
	</skill>
	<skill id="3704" levels="1" name="Doom Helmet">
		<!-- Confirmed CT2.5 -->
		<set name="target" val="TARGET_SELF" />
		<set name="skillType" val="BUFF" />
		<set name="operateType" val="OP_PASSIVE" />
		<for>
			<add order="0x40" stat="breath" val="50" />
			<mul order="0x30" stat="pAtk" val="1.0062" />
			<mul order="0x30" stat="regMp" val="1.0062" />
			<sub order="0x40" stat="poisonVuln" val="2" />
		</for>
	</skill>
	<skill id="3705" levels="1" name="Doom Gloves">
		<!-- Confirmed CT2.5 -->
		<set name="target" val="TARGET_SELF" />
		<set name="skillType" val="BUFF" />
		<set name="operateType" val="OP_PASSIVE" />
		<for>
			<add order="0x40" stat="runSpd" val="1.16" />
			<add order="0x40" stat="breath" val="33" />
			<mul order="0x30" stat="regMp" val="1.0083" />
		</for>
	</skill>
	<skill id="3706" levels="1" name="Doom Boots">
		<!-- Confirmed CT2.5 -->
		<set name="target" val="TARGET_SELF" />
		<set name="skillType" val="BUFF" />
		<set name="operateType" val="OP_PASSIVE" />
		<for>
			<add order="0x40" stat="runSpd" val="1.16" />
			<add order="0x40" stat="breath" val="33" />
			<mul order="0x30" stat="regMp" val="1.0083" />
		</for>
	</skill>
	<skill id="3707" levels="1" name="Tunic of Doom">
		<!-- It has been changed so that a rare type upper armor is not manufactured during item creation. -->
		<set name="target" val="TARGET_NONE" />
		<set name="skillType" val="NOTDONE" />
		<set name="operateType" val="OP_PASSIVE" />
	</skill>
	<skill id="3708" levels="1" name="Stockings of Doom">
		<!-- Confirmed CT2.5 -->
		<set name="target" val="TARGET_SELF" />
		<set name="skillType" val="BUFF" />
		<set name="operateType" val="OP_PASSIVE" />
		<for>
			<add order="0x40" stat="runSpd" val="2.91" />
			<add order="0x40" stat="breath" val="88" />
			<mul order="0x30" stat="regMp" val="1.0208" />
		</for>
	</skill>
	<skill id="3709" levels="1" name="Doom Helmet">
		<!-- Confirmed CT2.5 -->
		<set name="target" val="TARGET_SELF" />
		<set name="skillType" val="BUFF" />
		<set name="operateType" val="OP_PASSIVE" />
		<for>
			<add order="0x40" stat="runSpd" val="1.75" />
			<add order="0x40" stat="breath" val="50" />
			<mul order="0x30" stat="regMp" val="1.0125" />
		</for>
	</skill>
	<skill id="3710" levels="1" name="Blue Wolf Breastplate">
		<!-- It has been changed so that a rare type upper armor is not manufactured during item creation. -->
		<set name="target" val="TARGET_NONE" />
		<set name="skillType" val="NOTDONE" />
		<set name="operateType" val="OP_PASSIVE" />
	</skill>
	<skill id="3711" levels="1" name="Blue Wolf Gaiters">
		<!-- Confirmed CT2.5 -->
		<set name="target" val="TARGET_SELF" />
		<set name="skillType" val="BUFF" />
		<set name="operateType" val="OP_PASSIVE" />
		<for>
			<add order="0x40" stat="runSpd" val="2.91" />
			<mul order="0x30" stat="regHp" val="1.0208" />
		</for>
	</skill>
	<skill id="3712" levels="1" name="Blue Wolf Boots">
		<!-- Confirmed CT2.5 -->
		<set name="target" val="TARGET_SELF" />
		<set name="skillType" val="BUFF" />
		<set name="operateType" val="OP_PASSIVE" />
		<for>
			<add order="0x40" stat="runSpd" val="1.16" />
			<mul order="0x30" stat="regHp" val="1.0083" />
		</for>
	</skill>
	<skill id="3713" levels="1" name="Blue Wolf Gloves">
		<!-- Confirmed CT2.5 -->
		<set name="target" val="TARGET_SELF" />
		<set name="skillType" val="BUFF" />
		<set name="operateType" val="OP_PASSIVE" />
		<for>
			<add order="0x40" stat="runSpd" val="1.16" />
			<mul order="0x30" stat="regHp" val="1.0083" />
		</for>
	</skill>
	<skill id="3714" levels="1" name="Blue Wolf Helmet">
		<!-- Confirmed CT2.5 -->
		<set name="target" val="TARGET_SELF" />
		<set name="skillType" val="BUFF" />
		<set name="operateType" val="OP_PASSIVE" />
		<for>
			<add order="0x40" stat="runSpd" val="1.75" />
			<mul order="0x30" stat="regHp" val="1.0125" />
		</for>
	</skill>
	<skill id="3715" levels="1" name="Blue Wolf Leather Armor">
		<!-- It has been changed so that a rare type upper armor is not manufactured during item creation. -->
		<set name="target" val="TARGET_NONE" />
		<set name="skillType" val="NOTDONE" />
		<set name="operateType" val="OP_PASSIVE" />
	</skill>
	<skill id="3716" levels="1" name="Blue Wolf Boots">
		<!-- Confirmed CT2.5 -->
		<set name="target" val="TARGET_SELF" />
		<set name="skillType" val="BUFF" />
		<set name="operateType" val="OP_PASSIVE" />
		<for>
			<mul order="0x30" stat="pDef" val="1.0088" />
		</for>
	</skill>
	<skill id="3717" levels="1" name="Blue Wolf Gloves">
		<!-- Confirmed CT2.5 -->
		<set name="target" val="TARGET_SELF" />
		<set name="skillType" val="BUFF" />
		<set name="operateType" val="OP_PASSIVE" />
		<for>
			<mul order="0x30" stat="pDef" val="1.0088" />
		</for>
	</skill>
	<skill id="3718" levels="1" name="Blue Wolf Helmet">
		<!-- Confirmed CT2.5 -->
		<set name="target" val="TARGET_SELF" />
		<set name="skillType" val="BUFF" />
		<set name="operateType" val="OP_PASSIVE" />
		<for>
			<mul order="0x30" stat="pDef" val="1.0132" />
		</for>
	</skill>
	<skill id="3719" levels="1" name="Blue Wolf Boots">
		<!-- Confirmed CT2.5 -->
		<set name="target" val="TARGET_SELF" />
		<set name="skillType" val="BUFF" />
		<set name="operateType" val="OP_PASSIVE" />
		<for>
			<add order="0x40" stat="maxMp" val="34" />
			<mul order="0x30" stat="regMp" val="1.0083" />
		</for>
	</skill>
	<skill id="3720" levels="1" name="Blue Wolf Gloves">
		<!-- Confirmed CT2.5 -->
		<set name="target" val="TARGET_SELF" />
		<set name="skillType" val="BUFF" />
		<set name="operateType" val="OP_PASSIVE" />
		<for>
			<add order="0x40" stat="maxMp" val="34" />
			<mul order="0x30" stat="regMp" val="1.0083" />
		</for>
	</skill>
	<skill id="3721" levels="1" name="Blue Wolf Tunic">
		<!-- It has been changed so that a rare type upper armor is not manufactured during item creation. -->
		<set name="target" val="TARGET_NONE" />
		<set name="skillType" val="NOTDONE" />
		<set name="operateType" val="OP_PASSIVE" />
	</skill>
	<skill id="3722" levels="1" name="Blue Wolf Stockings">
		<!-- Confirmed CT2.5 -->
		<set name="target" val="TARGET_SELF" />
		<set name="skillType" val="BUFF" />
		<set name="operateType" val="OP_PASSIVE" />
		<for>
			<add order="0x40" stat="maxMp" val="85" />
			<mul order="0x30" stat="regMp" val="1.0208" />
		</for>
	</skill>
	<skill id="3723" levels="1" name="Blue Wolf Helmet">
		<!-- Confirmed CT2.5 -->
		<set name="target" val="TARGET_SELF" />
		<set name="skillType" val="BUFF" />
		<set name="operateType" val="OP_PASSIVE" />
		<for>
			<add order="0x40" stat="maxMp" val="51" />
			<mul order="0x30" stat="regMp" val="1.0125" />
		</for>
	</skill>
	<skill id="3724" levels="1" name="Dark Crystal Helmet">
		<!-- Confirmed CT2.5 -->
		<set name="target" val="TARGET_SELF" />
		<set name="skillType" val="BUFF" />
		<set name="operateType" val="OP_PASSIVE" />
		<for>
			<mul order="0x30" stat="gainHp" val="1.01" />
			<sub order="0x40" stat="paralyzeVuln" val="7.5" />
		</for>
	</skill>
	<skill id="3725" levels="1" name="Dark Crystal Breastplate">
		<!-- It has been changed so that a rare type upper armor is not manufactured during item creation. -->
		<set name="target" val="TARGET_NONE" />
		<set name="skillType" val="NOTDONE" />
		<set name="operateType" val="OP_PASSIVE" />
	</skill>
	<skill id="3726" levels="1" name="Dark Crystal Gaiters">
		<!-- Confirmed CT2.5 -->
		<set name="target" val="TARGET_SELF" />
		<set name="skillType" val="BUFF" />
		<set name="operateType" val="OP_PASSIVE" />
		<for>
			<mul order="0x30" stat="gainHp" val="1.02" />
			<sub order="0x40" stat="paralyzeVuln" val="12.5" />
		</for>
	</skill>
	<skill id="3727" levels="1" name="Dark Crystal Gloves">
		<!-- Confirmed CT2.5 -->
		<set name="target" val="TARGET_SELF" />
		<set name="skillType" val="BUFF" />
		<set name="operateType" val="OP_PASSIVE" />
		<for>
			<mul order="0x30" stat="gainHp" val="1.01" />
			<sub order="0x40" stat="paralyzeVuln" val="5" />
		</for>
	</skill>
	<skill id="3728" levels="1" name="Dark Crystal Boots">
		<!-- Confirmed CT2.5 -->
		<set name="target" val="TARGET_SELF" />
		<set name="skillType" val="BUFF" />
		<set name="operateType" val="OP_PASSIVE" />
		<for>
			<mul order="0x30" stat="gainHp" val="1.01" />
			<sub order="0x40" stat="paralyzeVuln" val="5" />
		</for>
	</skill>
	<skill id="3729" levels="1" name="Dark Crystal Shield">
		<!-- Confirmed CT2.5 -->
		<set name="target" val="TARGET_SELF" />
		<set name="skillType" val="BUFF" />
		<set name="operateType" val="OP_PASSIVE" />
		<for>
			<mul order="0x30" stat="mDef" val="1.02" />
		</for>
	</skill>
	<skill id="3730" levels="1" name="Dark Crystal Leather Armor">
		<!-- It has been changed so that a rare type upper armor is not manufactured during item creation. -->
		<set name="target" val="TARGET_NONE" />
		<set name="skillType" val="NOTDONE" />
		<set name="operateType" val="OP_PASSIVE" />
	</skill>
	<skill id="3731" levels="1" name="Dark Crystal Gloves">
		<!-- Confirmed CT2.5 -->
		<set name="target" val="TARGET_SELF" />
		<set name="skillType" val="BUFF" />
		<set name="operateType" val="OP_PASSIVE" />
		<for>
			<mul order="0x30" stat="pAtkSpd" val="1.0041" />
			<mul order="0x30" stat="pAtk" val="1.0041" />
			<sub order="0x40" stat="paralyzeVuln" val="5" />
		</for>
	</skill>
	<skill id="3732" levels="1" name="Dark Crystal Boots">
		<!-- Confirmed CT2.5 -->
		<set name="target" val="TARGET_SELF" />
		<set name="skillType" val="BUFF" />
		<set name="operateType" val="OP_PASSIVE" />
		<for>
			<mul order="0x30" stat="pAtkSpd" val="1.0041" />
			<mul order="0x30" stat="pAtk" val="1.0041" />
			<sub order="0x40" stat="paralyzeVuln" val="5" />
		</for>
	</skill>
	<skill id="3733" levels="1" name="Dark Crystal Helmet">
		<!-- Confirmed CT2.5 -->
		<set name="target" val="TARGET_SELF" />
		<set name="skillType" val="BUFF" />
		<set name="operateType" val="OP_PASSIVE" />
		<for>
			<mul order="0x30" stat="pAtkSpd" val="1.0062" />
			<mul order="0x30" stat="pAtk" val="1.0062" />
			<sub order="0x40" stat="paralyzeVuln" val="7.5" />
		</for>
	</skill>
	<skill id="3734" levels="1" name="Dark Crystal Leggings">
		<!-- Confirmed CT2.5 -->
		<set name="target" val="TARGET_SELF" />
		<set name="skillType" val="BUFF" />
		<set name="operateType" val="OP_PASSIVE" />
		<for>
			<mul order="0x30" stat="pAtkSpd" val="1.0103" />
			<mul order="0x30" stat="pAtk" val="1.0103" />
			<sub order="0x40" stat="paralyzeVuln" val="12.5" />
		</for>
	</skill>
	<skill id="3735" levels="1" name="Dark Crystal Gloves">
		<!-- Confirmed CT2.5 -->
		<set name="target" val="TARGET_SELF" />
		<set name="skillType" val="BUFF" />
		<set name="operateType" val="OP_PASSIVE" />
		<for>
			<mul order="0x30" stat="pDef" val="1.0133" />
			<add order="0x40" stat="runSpd" val="1.16" />
			<sub order="0x40" stat="cancel" val="8" />
			<sub order="0x40" stat="paralyzeVuln" val="8.33" />
		</for>
	</skill>
	<skill id="3736" levels="1" name="Dark Crystal Robe">
		<!-- It has been changed so that a rare type upper armor is not manufactured during item creation. -->
		<set name="target" val="TARGET_NONE" />
		<set name="skillType" val="NOTDONE" />
		<set name="operateType" val="OP_PASSIVE" />
	</skill>
	<skill id="3737" levels="1" name="Dark Crystal Boots">
		<!-- Confirmed CT2.5 -->
		<set name="target" val="TARGET_SELF" />
		<set name="skillType" val="BUFF" />
		<set name="operateType" val="OP_PASSIVE" />
		<for>
			<mul order="0x30" stat="pDef" val="1.0133" />
			<add order="0x40" stat="runSpd" val="1.16" />
			<sub order="0x40" stat="cancel" val="8" />
			<sub order="0x40" stat="paralyzeVuln" val="8.33" />
		</for>
	</skill>
	<skill id="3738" levels="1" name="Dark Crystal Helmet">
		<!-- Confirmed CT2.5 -->
		<set name="target" val="TARGET_SELF" />
		<set name="skillType" val="BUFF" />
		<set name="operateType" val="OP_PASSIVE" />
		<for>
			<mul order="0x30" stat="pDef" val="1.02" />
			<add order="0x40" stat="runSpd" val="1.75" />
			<sub order="0x40" stat="cancel" val="13" />
			<sub order="0x40" stat="paralyzeVuln" val="12.5" />
		</for>
	</skill>
	<skill id="3739" levels="1" name="Tallum Gloves">
		<!-- Confirmed CT2.5 -->
		<set name="target" val="TARGET_SELF" />
		<set name="skillType" val="BUFF" />
		<set name="operateType" val="OP_PASSIVE" />
		<for>
			<mul order="0x30" stat="pAtkSpd" val="1.0083" />
			<add order="0x40" stat="maxLoad" val="960" />
			<sub order="0x40" stat="poisonVuln" val="8" />
			<sub order="0x40" stat="bleedVuln" val="8" />
		</for>
	</skill>
	<skill id="3740" levels="1" name="Tallum Boots">
		<!-- Confirmed CT2.5 -->
		<set name="target" val="TARGET_SELF" />
		<set name="skillType" val="BUFF" />
		<set name="operateType" val="OP_PASSIVE" />
		<for>
			<mul order="0x30" stat="pAtkSpd" val="1.0083" />
			<add order="0x40" stat="maxLoad" val="960" />
			<sub order="0x40" stat="poisonVuln" val="8" />
			<sub order="0x40" stat="bleedVuln" val="8" />
		</for>
	</skill>
	<skill id="3741" levels="1" name="Tallum Plate Armor">
		<!-- It has been changed so that a rare type upper armor is not manufactured during item creation. -->
		<set name="target" val="TARGET_NONE" />
		<set name="skillType" val="NOTDONE" />
		<set name="operateType" val="OP_PASSIVE" />
	</skill>
	<skill id="3742" levels="1" name="Tallum Helmet">
		<!-- Confirmed CT2.5 -->
		<set name="target" val="TARGET_SELF" />
		<set name="skillType" val="BUFF" />
		<set name="operateType" val="OP_PASSIVE" />
		<for>
			<mul order="0x30" stat="pAtkSpd" val="1.0125" />
			<add order="0x40" stat="maxLoad" val="1440" />
			<sub order="0x40" stat="poisonVuln" val="12" />
			<sub order="0x40" stat="bleedVuln" val="12" />
		</for>
	</skill>
	<skill id="3743" levels="1" name="Tallum Leather Armor">
		<!-- It has been changed so that a rare type upper armor is not manufactured during item creation. -->
		<set name="target" val="TARGET_NONE" />
		<set name="skillType" val="NOTDONE" />
		<set name="operateType" val="OP_PASSIVE" />
	</skill>
	<skill id="3744" levels="1" name="Tallum Gloves">
		<!-- Confirmed CT2.5 -->
		<set name="target" val="TARGET_SELF" />
		<set name="skillType" val="BUFF" />
		<set name="operateType" val="OP_PASSIVE" />
		<for>
			<mul order="0x30" stat="regMp" val="1.0083" />
			<add order="0x40" stat="maxMp" val="37" />
			<sub order="0x40" stat="poisonVuln" val="8" />
			<sub order="0x40" stat="bleedVuln" val="8" />
		</for>
	</skill>
	<skill id="3745" levels="1" name="Tallum Boots">
		<!-- Confirmed CT2.5 -->
		<set name="target" val="TARGET_SELF" />
		<set name="skillType" val="BUFF" />
		<set name="operateType" val="OP_PASSIVE" />
		<for>
			<mul order="0x30" stat="regMp" val="1.0083" />
			<add order="0x40" stat="maxMp" val="37" />
			<sub order="0x40" stat="poisonVuln" val="8" />
			<sub order="0x40" stat="bleedVuln" val="8" />
		</for>
	</skill>
	<skill id="3746" levels="1" name="Tallum Helmet">
		<!-- Confirmed CT2.5 -->
		<set name="target" val="TARGET_SELF" />
		<set name="skillType" val="BUFF" />
		<set name="operateType" val="OP_PASSIVE" />
		<for>
			<mul order="0x30" stat="regMp" val="1.0125" />
			<add order="0x40" stat="maxMp" val="56" />
			<sub order="0x40" stat="poisonVuln" val="12" />
			<sub order="0x40" stat="bleedVuln" val="12" />
		</for>
	</skill>
	<skill id="3747" levels="1" name="Tallum Gloves">
		<!-- Confirmed CT2.5 -->
		<set name="target" val="TARGET_SELF" />
		<set name="skillType" val="BUFF" />
		<set name="operateType" val="OP_PASSIVE" />
		<for>
			<mul order="0x30" stat="mDef" val="1.0133" />
			<sub order="0x40" stat="poisonVuln" val="13.33" />
			<sub order="0x40" stat="bleedVuln" val="13.33" />
		</for>
	</skill>
	<skill id="3748" levels="1" name="Tallum Boots">
		<!-- Confirmed CT2.5 -->
		<set name="target" val="TARGET_SELF" />
		<set name="skillType" val="BUFF" />
		<set name="operateType" val="OP_PASSIVE" />
		<for>
			<mul order="0x30" stat="mDef" val="1.0133" />
			<sub order="0x40" stat="poisonVuln" val="13.33" />
			<sub order="0x40" stat="bleedVuln" val="13.33" />
		</for>
	</skill>
	<skill id="3749" levels="1" name="Tallum Tunic">
		<!-- It has been changed so that a rare type upper armor is not manufactured during item creation. -->
		<set name="target" val="TARGET_NONE" />
		<set name="skillType" val="NOTDONE" />
		<set name="operateType" val="OP_PASSIVE" />
	</skill>
	<skill id="3750" levels="1" name="Tallum Stockings">
		<!-- Confirmed CT2.5 -->
		<set name="target" val="TARGET_SELF" />
		<set name="skillType" val="BUFF" />
		<set name="operateType" val="OP_PASSIVE" />
		<for>
			<mul order="0x30" stat="mDef" val="1.0333" />
			<sub order="0x40" stat="poisonVuln" val="33.33" />
			<sub order="0x40" stat="bleedVuln" val="33.33" />
		</for>
	</skill>
	<skill id="3751" levels="1" name="Tallum Helmet">
		<!-- Confirmed CT2.5 -->
		<set name="target" val="TARGET_SELF" />
		<set name="skillType" val="BUFF" />
		<set name="operateType" val="OP_PASSIVE" />
		<for>
			<mul order="0x30" stat="mDef" val="1.02" />
			<sub order="0x40" stat="poisonVuln" val="20" />
			<sub order="0x40" stat="bleedVuln" val="20" />
		</for>
	</skill>
	<skill id="3752" levels="1" name="Majestic Gauntlet">
		<!-- Confirmed CT2.5 -->
		<set name="target" val="TARGET_SELF" />
		<set name="skillType" val="BUFF" />
		<set name="operateType" val="OP_PASSIVE" />
		<for>
			<mul order="0x30" stat="pAtk" val="1.0041" />
			<add order="0x40" stat="accCombat" val="0.31" />
			<sub order="0x40" stat="stunVuln" val="8.33" />
		</for>
	</skill>
	<skill id="3753" levels="1" name="Majestic Circlet">
		<!-- Confirmed CT2.5 -->
		<set name="target" val="TARGET_SELF" />
		<set name="skillType" val="BUFF" />
		<set name="operateType" val="OP_PASSIVE" />
		<for>
			<mul order="0x30" stat="pAtk" val="1.0062" />
			<add order="0x40" stat="accCombat" val="0.47" />
			<sub order="0x40" stat="stunVuln" val="12.5" />
		</for>
	</skill>
	<skill id="3754" levels="1" name="Majestic Plate Armor">
		<!-- It has been changed so that a rare type upper armor is not manufactured during item creation. -->
		<set name="target" val="TARGET_NONE" />
		<set name="skillType" val="NOTDONE" />
		<set name="operateType" val="OP_PASSIVE" />
	</skill>
	<skill id="3755" levels="1" name="Majestic Boots">
		<!-- Confirmed CT2.5 -->
		<set name="target" val="TARGET_SELF" />
		<set name="skillType" val="BUFF" />
		<set name="operateType" val="OP_PASSIVE" />
		<for>
			<mul order="0x30" stat="pAtk" val="1.0062" />
			<add order="0x40" stat="accCombat" val="0.47" />
			<sub order="0x40" stat="stunVuln" val="8.33" />
		</for>
	</skill>
	<skill id="3756" levels="1" name="Majestic Gauntlet">
		<!-- Confirmed CT2.5 -->
		<set name="target" val="TARGET_SELF" />
		<set name="skillType" val="BUFF" />
		<set name="operateType" val="OP_PASSIVE" />
		<for>
			<mul order="0x30" stat="pAtk" val="1.0083">
				<using kind="Bow,Crossbow" />
			</mul>
			<add order="0x40" stat="maxMp" val="40" />
			<add order="0x40" stat="maxLoad" val="960" />
			<sub order="0x40" stat="stunVuln" val="8.33" />
		</for>
	</skill>
	<skill id="3757" levels="1" name="Majestic Leather Armor">
		<!-- It has been changed so that a rare type upper armor is not manufactured during item creation. -->
		<set name="target" val="TARGET_NONE" />
		<set name="skillType" val="NOTDONE" />
		<set name="operateType" val="OP_PASSIVE" />
	</skill>
	<skill id="3758" levels="1" name="Majestic Boots">
		<!-- Confirmed CT2.5 -->
		<set name="target" val="TARGET_SELF" />
		<set name="skillType" val="BUFF" />
		<set name="operateType" val="OP_PASSIVE" />
		<for>
			<mul order="0x30" stat="pAtk" val="1.0083">
				<using kind="Bow,Crossbow" />
			</mul>
			<add order="0x40" stat="maxMp" val="40" />
			<add order="0x40" stat="maxLoad" val="960" />
			<sub order="0x40" stat="stunVuln" val="8.33" />
		</for>
	</skill>
	<skill id="3759" levels="1" name="Majestic Circlet">
		<!-- Confirmed CT2.5 -->
		<set name="target" val="TARGET_SELF" />
		<set name="skillType" val="BUFF" />
		<set name="operateType" val="OP_PASSIVE" />
		<for>
			<mul order="0x30" stat="pAtk" val="1.0125">
				<using kind="Bow,Crossbow" />
			</mul>
			<add order="0x40" stat="maxMp" val="60" />
			<add order="0x40" stat="maxLoad" val="1440" />
			<sub order="0x40" stat="stunVuln" val="12.5" />
		</for>
	</skill>
	<skill id="3760" levels="1" name="Majestic Gauntlet">
		<!-- Confirmed CT2.5 -->
		<set name="target" val="TARGET_SELF" />
		<set name="skillType" val="BUFF" />
		<set name="operateType" val="OP_PASSIVE" />
		<for>
			<add order="0x40" stat="maxMp" val="40" />
			<mul order="0x30" stat="regMp" val="1.0133" />
			<sub order="0x40" stat="stunVuln" val="8.33" />
		</for>
	</skill>
	<skill id="3761" levels="1" name="Majestic Robe">
		<!-- It has been changed so that a rare type upper armor is not manufactured during item creation. -->
		<set name="target" val="TARGET_NONE" />
		<set name="skillType" val="NOTDONE" />
		<set name="operateType" val="OP_PASSIVE" />
	</skill>
	<skill id="3762" levels="1" name="Majestic Boots">
		<!-- Confirmed CT2.5 -->
		<set name="target" val="TARGET_SELF" />
		<set name="skillType" val="BUFF" />
		<set name="operateType" val="OP_PASSIVE" />
		<for>
			<add order="0x40" stat="maxMp" val="40" />
			<mul order="0x30" stat="regMp" val="1.0133" />
			<sub order="0x40" stat="stunVuln" val="8.33" />
		</for>
	</skill>
	<skill id="3763" levels="1" name="Majestic Circlet">
		<!-- Confirmed CT2.5 -->
		<set name="target" val="TARGET_SELF" />
		<set name="skillType" val="BUFF" />
		<set name="operateType" val="OP_PASSIVE" />
		<for>
			<add order="0x40" stat="maxMp" val="60" />
			<mul order="0x30" stat="regMp" val="1.02" />
			<sub order="0x40" stat="stunVuln" val="12.5" />
		</for>
	</skill>
	<skill id="3764" levels="1" name="Armor of Nightmare">
		<!-- It has been changed so that a rare type upper armor is not manufactured during item creation. -->
		<set name="target" val="TARGET_NONE" />
		<set name="skillType" val="NOTDONE" />
		<set name="operateType" val="OP_PASSIVE" />
	</skill>
	<skill id="3765" levels="1" name="Gauntlet of Nightmare">
		<!-- Confirmed CT2.5 -->
		<set name="target" val="TARGET_SELF" />
		<set name="skillType" val="BUFF" />
		<set name="operateType" val="OP_PASSIVE" />
		<for>
			<mul order="0x30" stat="pAtk" val="1.0083" />
			<sub order="0x40" stat="sleepVuln" val="11.66" />
			<sub order="0x40" stat="rootVuln" val="11.66" />
		</for>
	</skill>
	<skill id="3766" levels="1" name="Boots of Nightmare">
		<!-- Confirmed CT2.5 -->
		<set name="target" val="TARGET_SELF" />
		<set name="skillType" val="BUFF" />
		<set name="operateType" val="OP_PASSIVE" />
		<for>
			<mul order="0x30" stat="pAtk" val="1.0083" />
			<sub order="0x40" stat="sleepVuln" val="11.66" />
			<sub order="0x40" stat="rootVuln" val="11.66" />
		</for>
	</skill>
	<skill id="3767" levels="1" name="Helm of Nightmare">
		<!-- Confirmed CT2.5 -->
		<set name="target" val="TARGET_SELF" />
		<set name="skillType" val="BUFF" />
		<set name="operateType" val="OP_PASSIVE" />
		<for>
			<mul order="0x30" stat="pAtk" val="1.0125" />
			<sub order="0x40" stat="sleepVuln" val="17.5" />
			<sub order="0x40" stat="rootVuln" val="17.5" />
		</for>
	</skill>
	<skill id="3768" levels="1" name="Nightmarish Leather Armor">
		<!-- It has been changed so that a rare type upper armor is not manufactured during item creation. -->
		<set name="target" val="TARGET_NONE" />
		<set name="skillType" val="NOTDONE" />
		<set name="operateType" val="OP_PASSIVE" />
	</skill>
	<skill id="3769" levels="1" name="Gauntlet of Nightmare">
		<!-- Confirmed CT2.5 -->
		<set name="target" val="TARGET_SELF" />
		<set name="skillType" val="BUFF" />
		<set name="operateType" val="OP_PASSIVE" />
		<for>
			<mul order="0x30" stat="pAtk" val="1.0041" />
			<sub order="0x40" stat="sleepVuln" val="11.66" />
			<sub order="0x40" stat="rootVuln" val="11.66" />
		</for>
	</skill>
	<skill id="3770" levels="1" name="Boots of Nightmare">
		<!-- Confirmed CT2.5 -->
		<set name="target" val="TARGET_SELF" />
		<set name="skillType" val="BUFF" />
		<set name="operateType" val="OP_PASSIVE" />
		<for>
			<mul order="0x30" stat="pAtk" val="1.0041" />
			<sub order="0x40" stat="sleepVuln" val="11.66" />
			<sub order="0x40" stat="rootVuln" val="11.66" />
		</for>
	</skill>
	<skill id="3771" levels="1" name="Gauntlet of Nightmare">
		<!-- Confirmed CT2.5 -->
		<set name="target" val="TARGET_SELF" />
		<set name="skillType" val="BUFF" />
		<set name="operateType" val="OP_PASSIVE" />
		<for>
			<mul order="0x30" stat="regMp" val="1.0041" />
			<mul order="0x30" stat="mAtk" val="1.0041" />
			<sub order="0x40" stat="sleepVuln" val="11.66" />
			<sub order="0x40" stat="rootVuln" val="11.66" />
		</for>
	</skill>
	<skill id="3772" levels="1" name="Nightmare Robe">
		<!-- It has been changed so that a rare type upper armor is not manufactured during item creation. -->
		<set name="target" val="TARGET_NONE" />
		<set name="skillType" val="NOTDONE" />
		<set name="operateType" val="OP_PASSIVE" />
	</skill>
	<skill id="3773" levels="1" name="Boots of Nightmare">
		<!-- Confirmed CT2.5 -->
		<set name="target" val="TARGET_SELF" />
		<set name="skillType" val="BUFF" />
		<set name="operateType" val="OP_PASSIVE" />
		<for>
			<mul order="0x30" stat="regMp" val="1.0041" />
			<mul order="0x30" stat="mAtk" val="1.0041" />
			<sub order="0x40" stat="sleepVuln" val="11.66" />
			<sub order="0x40" stat="rootVuln" val="11.66" />
		</for>
	</skill>
	<skill id="3774" levels="1" name="Shield of Nightmare">
		<!-- Confirmed CT2.5 -->
		<set name="target" val="TARGET_SELF" />
		<set name="skillType" val="BUFF" />
		<set name="operateType" val="OP_PASSIVE" />
		<for>
			<mul order="0x30" stat="mDef" val="1.02" />
		</for>
	</skill>
	<skill id="3775" levels="1" name="Draconic Leather Gloves">
		<!-- Confirmed CT2.5 -->
		<set name="target" val="TARGET_SELF" />
		<set name="skillType" val="BUFF" />
		<set name="operateType" val="OP_PASSIVE" />
		<for>
			<mul order="0x30" stat="pAtkSpd" val="1.0041" />
			<mul order="0x30" stat="pAtk" val="1.0041" />
			<add order="0x40" stat="maxMp" val="74" />
			<add order="0x40" stat="maxLoad" val="960" />
		</for>
	</skill>
	<skill id="3776" levels="1" name="Draconic Leather Boots">
		<!-- Confirmed CT2.5 -->
		<set name="target" val="TARGET_SELF" />
		<set name="skillType" val="BUFF" />
		<set name="operateType" val="OP_PASSIVE" />
		<for>
			<mul order="0x30" stat="pAtkSpd" val="1.0041" />
			<mul order="0x30" stat="pAtk" val="1.0041" />
			<add order="0x40" stat="maxMp" val="74" />
			<add order="0x40" stat="maxLoad" val="960" />
		</for>
	</skill>
	<skill id="3777" levels="1" name="Draconic Leather Armor">
		<!-- It has been changed so that a rare type upper armor is not manufactured during item creation. -->
		<set name="target" val="TARGET_NONE" />
		<set name="skillType" val="NOTDONE" />
		<set name="operateType" val="OP_PASSIVE" />
	</skill>
	<skill id="3778" levels="1" name="Draconic Leather Helmet">
		<!-- Confirmed CT2.5 -->
		<set name="target" val="TARGET_SELF" />
		<set name="skillType" val="BUFF" />
		<set name="operateType" val="OP_PASSIVE" />
		<for>
			<mul order="0x30" stat="pAtkSpd" val="1.0062" />
			<mul order="0x30" stat="pAtk" val="1.0062" />
			<add order="0x40" stat="maxMp" val="111" />
			<add order="0x40" stat="maxLoad" val="1440" />
		</for>
	</skill>
	<skill id="3779" levels="1" name="Major Arcana Gloves">
		<!-- Confirmed CT2.5 -->
		<set name="target" val="TARGET_SELF" />
		<set name="skillType" val="BUFF" />
		<set name="operateType" val="OP_PASSIVE" />
		<for>
			<mul order="0x30" stat="mAtk" val="1.0041" />
			<add order="0x40" stat="runSpd" val="1.16" />
			<sub order="0x40" stat="cancel" val="8" />
			<add order="0x40" stat="maxLoad" val="960" />
			<sub order="0x40" stat="stunVuln" val="8.3" />
		</for>
	</skill>
	<skill id="3780" levels="1" name="Major Arcana Robe">
		<!-- It has been changed so that a rare type upper armor is not manufactured during item creation. -->
		<set name="target" val="TARGET_NONE" />
		<set name="skillType" val="NOTDONE" />
		<set name="operateType" val="OP_PASSIVE" />
	</skill>
	<skill id="3781" levels="1" name="Major Arcana Boots">
		<!-- Confirmed CT2.5 -->
		<set name="target" val="TARGET_SELF" />
		<set name="skillType" val="BUFF" />
		<set name="operateType" val="OP_PASSIVE" />
		<for>
			<mul order="0x30" stat="mAtk" val="1.0041" />
			<add order="0x40" stat="runSpd" val="1.16" />
			<sub order="0x40" stat="cancel" val="8" />
			<add order="0x40" stat="maxLoad" val="960" />
			<sub order="0x40" stat="stunVuln" val="8.3" />
		</for>
	</skill>
	<skill id="3782" levels="1" name="Major Arcana Circlet">
		<!-- Confirmed CT2.5 -->
		<set name="target" val="TARGET_SELF" />
		<set name="skillType" val="BUFF" />
		<set name="operateType" val="OP_PASSIVE" />
		<for>
			<mul order="0x30" stat="mAtk" val="1.0062" />
			<add order="0x40" stat="runSpd" val="1.175" />
			<sub order="0x40" stat="cancel" val="13" />
			<add order="0x40" stat="maxLoad" val="1440" />
			<sub order="0x40" stat="stunVuln" val="12.5" />
		</for>
	</skill>
	<skill id="3783" levels="1" name="Imperial Crusader Gaiters">
		<!-- Confirmed CT2.5 -->
		<set name="target" val="TARGET_SELF" />
		<set name="skillType" val="BUFF" />
		<set name="operateType" val="OP_PASSIVE" />
		<for>
			<mul order="0x30" stat="pDef" val="1.0208" />
			<add order="0x40" stat="maxHp" val="185" />
			<sub order="0x40" stat="sleepVuln" val="17.5" />
			<sub order="0x40" stat="rootVuln" val="17.5" />
		</for>
	</skill>
	<skill id="3784" levels="1" name="Imperial Crusader Gauntlet">
		<!-- Confirmed CT2.5 -->
		<set name="target" val="TARGET_SELF" />
		<set name="skillType" val="BUFF" />
		<set name="operateType" val="OP_PASSIVE" />
		<for>
			<mul order="0x30" stat="pDef" val="1.083" />
			<add order="0x40" stat="maxHp" val="74" />
			<sub order="0x40" stat="sleepVuln" val="7" />
			<sub order="0x40" stat="rootVuln" val="7" />
		</for>
	</skill>
	<skill id="3785" levels="1" name="Imperial Crusader Boots">
		<!-- Confirmed CT2.5 -->
		<set name="target" val="TARGET_SELF" />
		<set name="skillType" val="BUFF" />
		<set name="operateType" val="OP_PASSIVE" />
		<for>
			<mul order="0x30" stat="pDef" val="1.083" />
			<add order="0x40" stat="maxHp" val="74" />
			<sub order="0x40" stat="sleepVuln" val="7" />
			<sub order="0x40" stat="rootVuln" val="7" />
		</for>
	</skill>
	<skill id="3786" levels="1" name="Imperial Crusader Shield">
		<!-- Confirmed CT2.5 -->
		<set name="target" val="TARGET_SELF" />
		<set name="skillType" val="BUFF" />
		<set name="operateType" val="OP_PASSIVE" />
		<for>
			<mul order="0x30" stat="mDef" val="1.02" />
		</for>
	</skill>
	<skill id="3787" levels="1" name="Imperial Crusader Helmet">
		<!-- Confirmed CT2.5 -->
		<set name="target" val="TARGET_SELF" />
		<set name="skillType" val="BUFF" />
		<set name="operateType" val="OP_PASSIVE" />
		<for>
			<mul order="0x30" stat="pDef" val="1.0125" />
			<add order="0x40" stat="maxHp" val="111" />
			<sub order="0x40" stat="sleepVuln" val="10.5" />
			<sub order="0x40" stat="rootVuln" val="10.5" />
		</for>
	</skill>
	<skill id="3788" levels="1" name="Imperial Crusader Breastplate">
		<!-- It has been changed so that a rare type upper armor is not manufactured during item creation. -->
		<set name="target" val="TARGET_NONE" />
		<set name="skillType" val="NOTDONE" />
		<set name="operateType" val="OP_PASSIVE" />
	</skill>
	<skill id="3789" levels="1" name="Dynasty Breastplate">
		<!-- It has been changed so that a rare type upper armor is not manufactured during item creation. -->
		<set name="target" val="TARGET_NONE" />
		<set name="skillType" val="NOTDONE" />
		<set name="operateType" val="OP_PASSIVE" />
	</skill>
	<skill id="3790" levels="1" name="Dynasty Gaiters">
		<!-- Confirmed CT2.5 -->
		<set name="target" val="TARGET_SELF" />
		<set name="skillType" val="BUFF" />
		<set name="operateType" val="OP_PASSIVE" />
		<for>
			<mul order="0x30" stat="pDef" val="1.0208" />
			<add order="0x40" stat="maxHp" val="205" />
			<add order="0x40" stat="darkRes" val="2" />
		</for>
	</skill>
	<skill id="3791" levels="1" name="Dynasty Gauntlet">
		<!-- Confirmed CT2.5 -->
		<set name="target" val="TARGET_SELF" />
		<set name="skillType" val="BUFF" />
		<set name="operateType" val="OP_PASSIVE" />
		<for>
			<mul order="0x30" stat="pDef" val="1.0083" />
			<add order="0x40" stat="maxHp" val="82" />
			<add order="0x40" stat="darkRes" val="0.8" />
		</for>
	</skill>
	<skill id="3792" levels="1" name="Dynasty Boots">
		<!-- Confirmed CT2.5 -->
		<set name="target" val="TARGET_SELF" />
		<set name="skillType" val="BUFF" />
		<set name="operateType" val="OP_PASSIVE" />
		<for>
			<mul order="0x30" stat="pDef" val="1.0083" />
			<add order="0x40" stat="maxHp" val="82" />
			<add order="0x40" stat="darkRes" val="0.8" />
		</for>
	</skill>
	<skill id="3793" levels="1" name="Dynasty Shield">
		<!-- Confirmed CT2.5 -->
		<set name="target" val="TARGET_SELF" />
		<set name="skillType" val="BUFF" />
		<set name="operateType" val="OP_PASSIVE" />
		<for>
			<mul order="0x30" stat="mDef" val="1.02" />
		</for>
	</skill>
	<skill id="3794" levels="1" name="Dynasty Helmet">
		<!-- Confirmed CT2.5 -->
		<set name="target" val="TARGET_SELF" />
		<set name="skillType" val="BUFF" />
		<set name="operateType" val="OP_PASSIVE" />
		<for>
			<mul order="0x30" stat="pDef" val="1.0125" />
			<add order="0x40" stat="maxHp" val="123" />
			<add order="0x40" stat="darkRes" val="1.2" />
		</for>
	</skill>
	<skill id="3795" levels="1" name="Dynasty Leather Armor">
		<!-- It has been changed so that a rare type upper armor is not manufactured during item creation. -->
		<set name="target" val="TARGET_NONE" />
		<set name="skillType" val="NOTDONE" />
		<set name="operateType" val="OP_PASSIVE" />
	</skill>
	<skill id="3796" levels="1" name="Dynasty Leather Leggings">
		<!-- Confirmed CT2.5 -->
		<set name="target" val="TARGET_SELF" />
		<set name="skillType" val="BUFF" />
		<set name="operateType" val="OP_PASSIVE" />
		<for>
			<add order="0x40" stat="accCombat" val="0.79" />
			<add order="0x40" stat="rEvas" val="0.79" />
			<add order="0x40" stat="maxHp" val="205" />
			<mul order="0x30" stat="pAtkSpd" val="1.0068" />
			<add order="0x40" stat="darkRes" val="2" />
		</for>
	</skill>
	<skill id="3797" levels="1" name="Dynasty Leather Boots">
		<!-- Confirmed CT2.5 -->
		<set name="target" val="TARGET_SELF" />
		<set name="skillType" val="BUFF" />
		<set name="operateType" val="OP_PASSIVE" />
		<for>
			<add order="0x40" stat="accCombat" val="0.31" />
			<add order="0x40" stat="rEvas" val="0.31" />
			<add order="0x40" stat="maxHp" val="82" />
			<mul order="0x30" stat="pAtkSpd" val="1.0027" />
			<add order="0x40" stat="darkRes" val="0.8" />
		</for>
	</skill>
	<skill id="3798" levels="1" name="Dynasty Leather Helmet">
		<!-- Confirmed CT2.5 -->
		<set name="target" val="TARGET_SELF" />
		<set name="skillType" val="BUFF" />
		<set name="operateType" val="OP_PASSIVE" />
		<for>
			<add order="0x40" stat="accCombat" val="0.47" />
			<add order="0x40" stat="rEvas" val="0.47" />
			<add order="0x40" stat="maxHp" val="123" />
			<mul order="0x30" stat="pAtkSpd" val="1.0041" />
			<add order="0x40" stat="darkRes" val="1.2" />
		</for>
	</skill>
	<skill id="3799" levels="1" name="Dynasty Tunic">
		<!-- It has been changed so that a rare type upper armor is not manufactured during item creation. -->
		<set name="target" val="TARGET_NONE" />
		<set name="skillType" val="NOTDONE" />
		<set name="operateType" val="OP_PASSIVE" />
	</skill>
</list>